functoolsex/__init__.py
functoolsex/func.py
functoolsex/iters.py
functoolsex/recur.py
functoolsex/tests.py
functoolsex-2.1.0.dist-info/licenses/LICENSE
functoolsex-2.1.0.dist-info/METADATA
functoolsex-2.1.0.dist-info/WHEEL
functoolsex-2.1.0.dist-info/top_level.txt
functoolsex-2.1.0.dist-info/RECORD
